pycobol/__init__.py
pycobol/arbrezone.py
pycobol/comportement.py
pycobol/execution.py
pycobol/extracteurs.py
pycobol/parser_cobol.py
pycobol/redefine.py
pycobol/zonage.py
pycobol/zonegroupe.py
pycobol/zonesimple.py
pycobol-0.1.0.dist-info/WHEEL
pycobol-0.1.0.dist-info/METADATA
pycobol-0.1.0.dist-info/RECORD
