Metadata-Version: 2.1
Name: pycobol
Version: 0.1.0
Summary: make cobol in python or python like cobol
Home-page: https://github.com/germanlinux/pycobol
License: MIT
Keywords: cobol,parser
Author: Eric German
Author-email: german.eric@gmail.com
Requires-Python: >=3.9,<4.0
Classifier: License :: OSI Approved :: MIT License
Classifier: Programming Language :: Python :: 3
Classifier: Programming Language :: Python :: 3.10
Classifier: Programming Language :: Python :: 3.9
Project-URL: Documentation, https://pycobol.readthedocs.io/fr/latest/
Project-URL: Repository, https://github.com/germanlinux/pycobol
